<?xml version="1.0" encoding="utf-8"?>
<templateItems template="/Templates/SculptureDetail.dwt" codeOutsideHTMLIsLocked="false">
   	<parameter name="name" type="text" passthrough="false"><![CDATA[Philosophy of Tides]]></parameter>
   	<parameter name="meta_description" type="text" passthrough="false"><![CDATA[The central image in this work is that of a combat field stretcher in use during the Second World War . The ripped and frayed canvas stretched across the wooden poles is repaired with vintage catgut issued for emergency field sutures. All of the voids are remediated with beeswax as well.]]></parameter>
   	<parameter name="main_image_src" type="text" passthrough="false"><![CDATA[/assets/images/philosophy-of-tides-1.jpg]]></parameter>
	<parameter name="another_view_1" type="boolean" passthrough="false">true</parameter>
	<parameter name="another_view_1_src" type="text" passthrough="false"><![CDATA[/assets/images/philosophy-of-tides-upper-detail-3.jpg]]></parameter>
	<parameter name="another_view_2" type="boolean" passthrough="false">true</parameter>
	<parameter name="another_view_2_src" type="text" passthrough="false"><![CDATA[/assets/images/philosophy-of-tides-lower-detail-2.jpg]]></parameter>
	<parameter name="video" type="boolean" passthrough="false">false</parameter>
	<parameter name="video_src" type="text" passthrough="false"></parameter>
	<parameter name="video_poster" type="text" passthrough="false"><![CDATA[]]></parameter>
	<parameter name="has_prev" type="boolean" passthrough="false">true</parameter>
	<parameter name="has_next" type="boolean" passthrough="false">true</parameter>
	<parameter name="prev" type="text" passthrough="false"><![CDATA[oxherding-sea-of-teeth.html]]></parameter>
	<parameter name="next" type="text" passthrough="false"><![CDATA[supplicant-ii.html]]></parameter>
   	<item name="materials"><![CDATA[canvas, wood, bronze, beeswax, steel, pigments]]></item>
	<item name="dimensions"><![CDATA[103&Prime; &times; 37&Prime; &times; 25&Prime;]]></item>
	<item name="description"><![CDATA[
					<p class="description">The central image in this work is that of a combat field stretcher in use during the Second World War . The ripped and frayed canvas stretched across the wooden poles is repaired with vintage catgut issued for emergency field sutures. All of the voids are remediated with beeswax as well.</p>
                    <p class="description">With some irony the canvas lends itself to the application of diagrams and images that reference human reproduction and planetary/stellar positions. This admixed mapping of information was culled from biological and astronomical charts used by educators at the turn of the 19th century. The additional cast metal and wax images further contextualize the piece in terms of its adverting to the longevity of the information with which we orient ourselves.</p>
		]]></item>
   	<item name="head"><![CDATA[]]></item>
</templateItems>